{"cameraMode":{"drawMode":0,"name":"Shaded","section":"Shading Mode"},"sceneLighting":true,"audioPlay":false,"sceneViewState":{"m_AlwaysRefresh":false,"showFog":true,"showSkybox":true,"showFlares":true,"showImageEffects":true,"showParticleSystems":true,"showVisualEffectGraphs":true,"m_FxEnabled":true},"in2DMode":false,"pivot":{"x":-19.137828826904298,"y":-11.750917434692383,"z":-20.129194259643556},"rotation":{"x":0.11973366886377335,"y":-0.873925507068634,"z":0.27207517623901369,"w":0.384632408618927},"size":13.212603569030762,"orthographic":false}